<?xml version="1.0" encoding="UTF-8"?>
<persistence version="2.0" xmlns="http://java.sun.com/xml/ns/persistence" xmlns:xsi="http://www.w3.org/2001/XMLSchema-instance" xsi:schemaLocation="http://java.sun.com/xml/ns/persistence http://java.sun.com/xml/ns/persistence/persistence_2_0.xsd">
	<persistence-unit name="ConectelPU" transaction-type="JTA">
	    <jta-data-source>jdbc/mysql</jta-data-source>
		<class>mx.com.gahm.conenctel.entities.PerfilDO</class>
		<class>mx.com.gahm.conenctel.entities.UsuarioDO</class>
		<class>mx.com.gahm.conenctel.entities.ClienteDO</class>
		<class>mx.com.gahm.conenctel.entities.ContactoDO</class>
		<class>mx.com.gahm.conenctel.entities.DatosComercialesDO</class>
		<class>mx.com.gahm.conenctel.entities.ProductoDO</class>
		<class>mx.com.gahm.conenctel.entities.AplicaDO</class>
		<class>mx.com.gahm.conenctel.entities.CategoriaDO</class>
		<class>mx.com.gahm.conenctel.entities.ColaboradorDO</class>
		<class>mx.com.gahm.conenctel.entities.ConfigPruebaEntregaDO</class>
		<class>mx.com.gahm.conenctel.entities.DatosGrlsProyectoDO</class>
		<class>mx.com.gahm.conenctel.entities.DatosGrlsProyectoImplDO</class>
		<class>mx.com.gahm.conenctel.entities.EntregableDO</class>
		<class>mx.com.gahm.conenctel.entities.EstadoDO</class>
		<class>mx.com.gahm.conenctel.entities.ImputableDO</class>
		<class>mx.com.gahm.conenctel.entities.ObservacionDO</class>
		<class>mx.com.gahm.conenctel.entities.PantallaDO</class>
		<class>mx.com.gahm.conenctel.entities.ParametroDO</class>
		<class>mx.com.gahm.conenctel.entities.PerfilPantallaDO</class>
		<class>mx.com.gahm.conenctel.entities.TipoServicioDO</class>
		<class>mx.com.gahm.conenctel.entities.ProyectoDO</class>
		<class>mx.com.gahm.conenctel.entities.ProyectoEntregableDO</class>
		<class>mx.com.gahm.conenctel.entities.RequisicionDO</class>
		<class>mx.com.gahm.conenctel.entities.TipoColaboradorDO</class>
		<class>mx.com.gahm.conenctel.entities.TipoEntregableDO</class>
		<class>mx.com.gahm.conenctel.entities.DesarrolloProyectoABDO</class>
		<class>mx.com.gahm.conenctel.entities.SeguimientoDO</class>
		<class>mx.com.gahm.conenctel.entities.AreaSolicitanteDO</class>
		<class>mx.com.gahm.conenctel.entities.ComentarioDO</class>
		<class>mx.com.gahm.conenctel.entities.CompaniaDO</class>
		<class>mx.com.gahm.conenctel.entities.ConsumibleDO</class>
		<class>mx.com.gahm.conenctel.entities.DescripcionAlmacenDO</class>
		<class>mx.com.gahm.conenctel.entities.DocumentoAlmacenDO</class>
		<class>mx.com.gahm.conenctel.entities.EquipoMedicionDO</class>
		<class>mx.com.gahm.conenctel.entities.EquipoTransporteDO</class>
		<class>mx.com.gahm.conenctel.entities.EstatusADO</class>
		<class>mx.com.gahm.conenctel.entities.EstatusBDO</class>
		<class>mx.com.gahm.conenctel.entities.EstatusCDO</class>
		<class>mx.com.gahm.conenctel.entities.GrupoFamiliaADO</class>
		<class>mx.com.gahm.conenctel.entities.GrupoFamiliaBDO</class>
		<class>mx.com.gahm.conenctel.entities.GrupoFamiliaCDO</class>
		<class>mx.com.gahm.conenctel.entities.GrupoFamiliaDDO</class>
		<class>mx.com.gahm.conenctel.entities.GrupoFamiliaEDO</class>
		<class>mx.com.gahm.conenctel.entities.GrupoFamiliaFDO</class>
		<class>mx.com.gahm.conenctel.entities.HardwareDO</class>
		<class>mx.com.gahm.conenctel.entities.HerramientaDO</class>
		<class>mx.com.gahm.conenctel.entities.MaterialDO</class>
		<class>mx.com.gahm.conenctel.entities.NombreSolicitanteDO</class>
		<class>mx.com.gahm.conenctel.entities.PrioridadDO</class>
		<class>mx.com.gahm.conenctel.entities.ServicioSolicitadoDO</class>
		<class>mx.com.gahm.conenctel.entities.SoftwareDO</class>
		<class>mx.com.gahm.conenctel.entities.SolicitudAlmacenDO</class>
		<class>mx.com.gahm.conenctel.entities.TelefoniaMovilDO</class>
		<class>mx.com.gahm.conenctel.entities.TipoAlmacenDO</class>
		<class>mx.com.gahm.conenctel.entities.TipoDocumentoAlmacenDO</class>
		<class>mx.com.gahm.conenctel.entities.TipoMantenimientoDO</class>
		<class>mx.com.gahm.conenctel.entities.UbicacionADO</class>
		<class>mx.com.gahm.conenctel.entities.UbicacionBDO</class>
		<class>mx.com.gahm.conenctel.entities.UbicacionCDO</class>
		<class>mx.com.gahm.conenctel.entities.UnidadADO</class>
		<class>mx.com.gahm.conenctel.entities.UnidadBDO</class>
		<class>mx.com.gahm.conenctel.entities.UnidadCDO</class>
		<class>mx.com.gahm.conenctel.entities.ProveedorDO</class>
		<class>mx.com.gahm.conenctel.entities.ProveedorSeleccionadoDO</class>
		<class>mx.com.gahm.conenctel.entities.TipoPersonaDO</class>
		<class>mx.com.gahm.conenctel.entities.ProveedorCalificadoDO</class>
		<class>mx.com.gahm.conenctel.entities.TipoPagoDO</class>
		<class>mx.com.gahm.conenctel.entities.DatoBancarioDO</class>
		<class>mx.com.gahm.conenctel.entities.ProveedorMaquiladorDO</class>
		<class>mx.com.gahm.conenctel.entities.TipoContratoDO</class>
		<class>mx.com.gahm.conenctel.entities.OrdenCompraDO</class>	
		<class>mx.com.gahm.conenctel.entities.UnidadOrdenCompraDO</class>
		<class>mx.com.gahm.conenctel.entities.CotizacionDO</class>
		<class>mx.com.gahm.conenctel.entities.RequisicionCompraDO</class>
		<class>mx.com.gahm.conenctel.entities.FormaPagoDO</class>
		<class>mx.com.gahm.conenctel.entities.PartidaRequisicionCompraDO</class>
		<class>mx.com.gahm.conenctel.entities.EstatusRequisicionCompraDO</class>
		<class>mx.com.gahm.conenctel.entities.ProyectoPadreDO</class>
		<class>mx.com.gahm.conenctel.entities.ProyectoPadreHijoDO</class>
		<class>mx.com.gahm.conenctel.entities.FacturaPorPagarDO</class>
		<class>mx.com.gahm.conenctel.entities.EstadoSolicitudServicioMaquiladoDO</class>
		<class>mx.com.gahm.conenctel.entities.OrdenCompraMaquiladoDO</class>
		<class>mx.com.gahm.conenctel.entities.EstadoValidacionOperativaDO</class>
		<class>mx.com.gahm.conenctel.entities.HerramientaSolicitudAlmacenDO</class>
		<class>mx.com.gahm.conenctel.entities.EstadoSolicitudAlmacenDO</class>
		<class>mx.com.gahm.conenctel.entities.ValidacionProyectoDO</class>
		<class>mx.com.gahm.conenctel.entities.ComentarioComprasDO</class>
		<class>mx.com.gahm.conenctel.entities.ComentarioRequisicionDO</class>
		<class>mx.com.gahm.conenctel.entities.SolicitudServicioMaquiladoDO</class>
		<class>mx.com.gahm.conenctel.entities.ConcentradoOrdenCompraClienteDO</class>
		<class>mx.com.gahm.conenctel.entities.SolicitanteRequisicionDO</class>
		<class>mx.com.gahm.conenctel.entities.ValidacionAdministrativaDO</class>
		<class>mx.com.gahm.conenctel.entities.EstadoValidacionAdministrativaDO</class>
		<class>mx.com.gahm.conenctel.entities.TipoValidacionAdministrativaDO</class>
		<class>mx.com.gahm.conenctel.entities.EstadoValidacionCobroDO</class>
		<class>mx.com.gahm.conenctel.entities.EstadoFinalValidacionDO</class>
		<class>mx.com.gahm.conenctel.entities.ComentarioValidacionAdministrativaDO</class>
		<class>mx.com.gahm.conenctel.entities.ComentarioPantallaValidacionAdministrativaDO</class>
		<class>mx.com.gahm.conenctel.entities.PartidaConcentradoOrdenCompraClienteDO</class>
		<class>mx.com.gahm.conenctel.entities.ComentarioConcentradoOrdenCompraClienteDO</class>
		<class>mx.com.gahm.conenctel.entities.OrdenCompraClienteDO</class>
		<class>mx.com.gahm.conenctel.entities.EstadoOrdenCompraDO</class>
		<class>mx.com.gahm.conenctel.entities.ValidacionCostoDO</class>
		<class>mx.com.gahm.conenctel.entities.ComentarioOrdenCompraClienteDO</class>
		<class>mx.com.gahm.conenctel.entities.ComentarioValidacionCostoOrdenCompraClienteDO</class>
		<class>mx.com.gahm.conenctel.entities.NotaCreditoClienteDO</class>
		<class>mx.com.gahm.conenctel.entities.ComentarioNotaCreditoClienteDO</class>
		<class>mx.com.gahm.conenctel.entities.ComentarioCuentasPagarFacturacionDO</class>
		<class>mx.com.gahm.conenctel.entities.InformacionFacturacionDO</class>
		<class>mx.com.gahm.conenctel.entities.ComentarioInformacionFacturacion3DO</class>
		<class>mx.com.gahm.conenctel.entities.ComentarioInformacionFacturacion2DO</class>
		<class>mx.com.gahm.conenctel.entities.ComentarioInformacionFacturacion1DO</class>
		<class>mx.com.gahm.conenctel.entities.NotaCreditoProveedorDO</class>
		<class>mx.com.gahm.conenctel.entities.EstadoInvestigacionCalidadDO</class>
		<class>mx.com.gahm.conenctel.entities.EstadoTesoreriaDO</class>
		<class>mx.com.gahm.conenctel.entities.FacturaProveedorDO</class>
		<class>mx.com.gahm.conenctel.entities.ComentarioFacturaProveedorDO</class>
		<class>mx.com.gahm.conenctel.entities.SolicitudViaticosDO</class>
		<class>mx.com.gahm.conenctel.entities.MedioTransporteDO</class>
		<class>mx.com.gahm.conenctel.entities.ComprobacionViaticosDO</class>
		<class>mx.com.gahm.conenctel.entities.EstadoComprobacionViaticosDO</class>
		<class>mx.com.gahm.conenctel.entities.MoviemientoFondoFijoCajaChicaDO</class>
		<class>mx.com.gahm.conenctel.entities.DescripcionFondoFijoCajaChicaDO</class>
		<class>mx.com.gahm.conenctel.entities.MovimientoPagoContableServicioDO</class>
		<class>mx.com.gahm.conenctel.entities.DescripcionPagoContableServicioDO</class>
		<class>mx.com.gahm.conenctel.entities.TipoOperacionDO</class>
		<class>mx.com.gahm.conenctel.entities.ComentarioMovimientoPagoContableServicioDO</class>
		<class>mx.com.gahm.conenctel.entities.ComentarioContabilidadDO</class>
		<class>mx.com.gahm.conenctel.entities.ComentarioMoviemientoFondoFijoCajaChicaDO</class>
		<class>mx.com.gahm.conenctel.entities.BancoConectelDO</class>
		<class>mx.com.gahm.conenctel.entities.CobranzaDO</class>
		<class>mx.com.gahm.conenctel.entities.ReclutamientoSolicitudEmpleoDO</class>
		<class>mx.com.gahm.conenctel.entities.TipoContratacionDO</class>
		<class>mx.com.gahm.conenctel.entities.SuspensionDO</class>
		<class>mx.com.gahm.conenctel.entities.MotivoTerminoContratoDO</class>
		<class>mx.com.gahm.conenctel.entities.EstadoColaboradorDO</class>
		<class>mx.com.gahm.conenctel.entities.InformacionConfidencialColaboradorDO</class>
		<class>mx.com.gahm.conenctel.entities.TipoCandidatoDO</class>
		<class>mx.com.gahm.conenctel.entities.FaseContratacionDO</class>
		<class>mx.com.gahm.conenctel.entities.ConceptoOtraOperacionFinancieraDO</class>
		<class>mx.com.gahm.conenctel.entities.ComentarioTesoreriaDO</class>
		<class>mx.com.gahm.conenctel.entities.ComentarioPagoOtraOperacionFinancieraDO</class>
		<class>mx.com.gahm.conenctel.entities.DatosPrincipalesSolicitanteDO</class>
		<class>mx.com.gahm.conenctel.entities.NacionalidadDO</class>
		<class>mx.com.gahm.conenctel.entities.IdentificacionDO</class>
		<class>mx.com.gahm.conenctel.entities.DocumentacionExtranjerosDO</class>
		<class>mx.com.gahm.conenctel.entities.EstadoCivilDO</class>
		<class>mx.com.gahm.conenctel.entities.SexoDO</class>
		<class>mx.com.gahm.conenctel.entities.DireccionSolicitanteDO</class>
		<class>mx.com.gahm.conenctel.entities.LicenciaDO</class>
		<class>mx.com.gahm.conenctel.entities.TipoLicenciaDO</class>
		<class>mx.com.gahm.conenctel.entities.CartaAntecedentesPenalesDO</class>
		<class>mx.com.gahm.conenctel.entities.EstadoSaludDO</class>
		<class>mx.com.gahm.conenctel.entities.TiempoLibreDO</class>
		<class>mx.com.gahm.conenctel.entities.DatosGeneralesSolicitanteDO</class>
		<class>mx.com.gahm.conenctel.entities.ViveConDO</class>
		<class>mx.com.gahm.conenctel.entities.DependientesDO</class>
		<class>mx.com.gahm.conenctel.entities.DatosFamiliaresSolicitanteDO</class>
		<class>mx.com.gahm.conenctel.entities.UltimoGradoEstudiosDO</class>
		<class>mx.com.gahm.conenctel.entities.EstadoAcademicoDO</class>
		<class>mx.com.gahm.conenctel.entities.DatosEscolaresHabilidadesDO</class>
		<class>mx.com.gahm.conenctel.entities.DatosUltimoEmpleoSolicitanteDO</class>
		<class>mx.com.gahm.conenctel.entities.FuenteReclutamientoDO</class>
		<class>mx.com.gahm.conenctel.entities.FaseSeleccionDO</class>
		<class>mx.com.gahm.conenctel.entities.DatosSobreConectelSolicitanteDO</class>
		<class>mx.com.gahm.conenctel.entities.ActividadTiempoLibreDO</class>
		<class>mx.com.gahm.conenctel.entities.ClaseIncidenciaDO</class>
		<class>mx.com.gahm.conenctel.entities.TipoIncapacidadDO</class>
		<class>mx.com.gahm.conenctel.entities.DeduccionDO</class>
		<class>mx.com.gahm.conenctel.entities.ClasificacionFaltaDO</class>
		<class>mx.com.gahm.conenctel.entities.ClasificacionPermisoDO</class>
		<class>mx.com.gahm.conenctel.entities.TipoSancionDO</class>
		<class>mx.com.gahm.conenctel.entities.FormaPagoPrenominaDO</class>
		<class>mx.com.gahm.conenctel.entities.PercepcionDO</class>
		<class>mx.com.gahm.conenctel.entities.VariacionDO</class>
		<class>mx.com.gahm.conenctel.entities.RegistroPercepcionDO</class>
		<class>mx.com.gahm.conenctel.entities.CursoDO</class>
		<class>mx.com.gahm.conenctel.entities.ComentarioPagoViaticosDO</class>
		<class>mx.com.gahm.conenctel.entities.RegistroDeduccionDO</class>
		<class>mx.com.gahm.conenctel.entities.ContratacionDO</class>
		<class>mx.com.gahm.conenctel.entities.ComentarioCobranzaDO</class>
		<class>mx.com.gahm.conenctel.entities.NoConformidadDO</class>
		<class>mx.com.gahm.conenctel.entities.AreaLevantaNoConformidadDO</class>
		<class>mx.com.gahm.conenctel.entities.ResultadoImplementacionDO</class>
		<class>mx.com.gahm.conenctel.entities.TipoAccionDO</class>
		<class>mx.com.gahm.conenctel.entities.FuenteNoConformidadDO</class>
		<class>mx.com.gahm.conenctel.entities.EstadoAccionPreventivaCorrectivaDO</class>
		<class>mx.com.gahm.conenctel.entities.AccionPreventivaCorrectivaDO</class>
		<class>mx.com.gahm.conenctel.entities.SeleccionReclutamientoDO</class>
		<class>mx.com.gahm.conenctel.entities.InformacionPrenominaDO</class>
		<class>mx.com.gahm.conenctel.entities.MinutaDO</class>
		<class>mx.com.gahm.conenctel.entities.ParticipanteMinutaDO</class>
		<class>mx.com.gahm.conenctel.entities.AcuerdoMinutaDO</class>
		<class>mx.com.gahm.conenctel.entities.TipoFormacionDO</class>
		<class>mx.com.gahm.conenctel.entities.TipoCapacitacionDO</class>
		<class>mx.com.gahm.conenctel.entities.DatosGeneralesProyectoDO</class>
		<class>mx.com.gahm.conenctel.entities.TipoAuditoriaDO</class>
		<class>mx.com.gahm.conenctel.entities.FormaAuditoriaDO</class>
		<class>mx.com.gahm.conenctel.entities.EstadoSistemaGestionDO</class>
 		<class>mx.com.gahm.conenctel.entities.EquipoOficinaDominaDO</class>
		<class>mx.com.gahm.conenctel.entities.ExamenPsicometricoDO</class>
		<class>mx.com.gahm.conenctel.entities.DocumentosContratacionDO</class>
		<class>mx.com.gahm.conenctel.entities.PerfilEscalaDO</class>
		<class>mx.com.gahm.conenctel.entities.PagoProveedorDO</class>
		<class>mx.com.gahm.conenctel.entities.PagoMovimientoPagoContableServicioDO</class>
		<class>mx.com.gahm.conenctel.entities.ComentarioPagoMovimientoPagoContableServicioDO</class>
		<class>mx.com.gahm.conenctel.entities.ComentarioPagoProveedorDO</class>
		<class>mx.com.gahm.conenctel.entities.ComentarioCotizacionDO</class>
		<class>mx.com.gahm.conenctel.entities.DocumentoComprobacionViaticosDO</class>
		<class>mx.com.gahm.conenctel.entities.ComentariosDO</class>
		<class>mx.com.gahm.conenctel.entities.ComentarioProveedorDO</class>
		<class>mx.com.gahm.conenctel.entities.DocumentoLiderProveedorMaquiladorDO</class>
		<class>mx.com.gahm.conenctel.entities.TipoDesarrolloProyectoDO</class>
		<class>mx.com.gahm.conenctel.entities.EstadoNotificacionDO</class>
		<class>mx.com.gahm.conenctel.entities.NotificacionDO</class>
		<class>mx.com.gahm.conenctel.entities.PrestacionesDO</class>
		<class>mx.com.gahm.conenctel.entities.NumeroFoliosFacturaFacturadosDO</class>
		<class>mx.com.gahm.conenctel.entities.NumeroProyectosCobradosDO</class>
		<class>mx.com.gahm.conenctel.entities.CalibracionDO</class>
		<class>mx.com.gahm.conenctel.entities.MantenimientoServicioDO</class>
		<class>mx.com.gahm.conenctel.entities.PagoDO</class>
		<class>mx.com.gahm.conenctel.entities.SolicitanteSolicitudViaticosDO</class>
		<class>mx.com.gahm.conenctel.entities.ComentarioSistemasGestionDO</class>
		<class>mx.com.gahm.conenctel.entities.ComentarioSugerenciaDO</class>
		<class>mx.com.gahm.conenctel.entities.FacturaProveedorPagoProveedorDO</class>
		<class>mx.com.gahm.conenctel.entities.NotaCreditoProveedorPagoProveedorDO</class>
		<class>mx.com.gahm.conenctel.entities.SolicitudPermisoDO</class>
		<class>mx.com.gahm.conenctel.entities.PermisoSinGoceSueldoDO</class>
		<class>mx.com.gahm.conenctel.entities.PermisoConGoceSueldoDO</class>
		<class>mx.com.gahm.conenctel.entities.ComentarioSolicitudPermisoDO</class>
		<class>mx.com.gahm.conenctel.entities.ComentarioRecursosHumanosDO</class>
		<class>mx.com.gahm.conenctel.entities.ComentarioSolicitudVacacionesDO</class>
		<class>mx.com.gahm.conenctel.entities.EstadisticaPersonalDO</class>
		<class>mx.com.gahm.conenctel.entities.TrimestreDO</class>
		<class>mx.com.gahm.conenctel.entities.AnoDO</class>
		<class>mx.com.gahm.conenctel.entities.RangoEstadisticaPersonalDO</class>
		<class>mx.com.gahm.conenctel.entities.ArchivoCotizacionDO</class>
		<class>mx.com.gahm.conenctel.entities.DocumentoAyudanteDO</class>
		<class>mx.com.gahm.conenctel.entities.EstatusDevolucionDO</class>
		<properties>
			<property name="eclipselink.logging.level" value="FINE"/> 
			<property name="eclipselink.logging.parameters" value="true"/>
			<!-- property name="hibernate.cache.use_query_cache" value="false"/ -->
			<property name="eclipselink.cache.shared.default" value="false"/>
		</properties>
	</persistence-unit>
</persistence>
